Metadata-Version: 1.0
Name: dgdR-distributions
Version: 1.0
Summary: Gaussian and Binomial distributions
Home-page: UNKNOWN
Author: Raghu Kula
Author-email: raghuvarankula@gmail.com
License: UNKNOWN
Platform: UNKNOWN
